{
  "type": "create:sequenced_assembly",
  "ingredient": {
    "tag": "foolish_asteroids:comet_medal"
  },
  "transitionalItem": {
    "item": "foolish_asteroids:incomplete_blank_medallion"
  },
  "sequence": [
    {
      "type": "create:deploying",
      "ingredients": [
        {
          "item": "foolish_asteroids:incomplete_blank_medallion"
        },
        [
          {
            "tag": "create:sandpaper"
          }
        ]
      ],
      "results": [
        {
          "item": "foolish_asteroids:incomplete_blank_medallion"
        }
      ]
    },
    {
      "type": "create:deploying",
      "ingredients": [
        {
          "item": "foolish_asteroids:incomplete_blank_medallion"
        },
        [
          {
            "tag": "create:sandpaper"
          }
        ]
      ],
      "results": [
        {
          "item": "foolish_asteroids:incomplete_blank_medallion"
        }
      ]
    },
    {
      "type": "create:deploying",
      "ingredients": [
        {
          "item": "foolish_asteroids:incomplete_blank_medallion"
        },
        [
          {
            "item": "dustrial_decor:industrial_iron_billet"
          }
        ]
      ],
      "results": [
        {
          "item": "foolish_asteroids:incomplete_blank_medallion"
        }
      ]
    }
  ],
  "results": [
    {
      "item": "foolish_asteroids:blank_medallion"
    }
  ],
  "loops": 1
}